aiopythonik/__init__.py
aiopythonik/_internal_utils.py
aiopythonik/client.py
aiopythonik/client.pyi
aiopythonik/helpers.py
aiopythonik/rate_limiting.py
aiopythonik/_pythonik_patches/__init__.py
aiopythonik/_pythonik_patches/_internal_utils.py
aiopythonik/_pythonik_patches/_logger.py
aiopythonik/_pythonik_patches/client.py
aiopythonik/_pythonik_patches/client.pyi
aiopythonik/_pythonik_patches/models.py
aiopythonik/_pythonik_patches/models.pyi
aiopythonik/_pythonik_patches/specs.py
aiopythonik/_pythonik_patches/specs.pyi
aiopythonik/specs/__init__.py
aiopythonik/specs/assets.py
aiopythonik/specs/assets.pyi
aiopythonik/specs/base.py
aiopythonik/specs/base.pyi
aiopythonik/specs/collection.py
aiopythonik/specs/collection.pyi
aiopythonik/specs/files.py
aiopythonik/specs/files.pyi
aiopythonik/specs/jobs.py
aiopythonik/specs/jobs.pyi
aiopythonik/specs/metadata.py
aiopythonik/specs/metadata.pyi
aiopythonik/specs/search.py
aiopythonik/specs/search.pyi
aiopythonik-2025.12b2.dist-info/licenses/LICENSE
aiopythonik-2025.12b2.dist-info/METADATA
aiopythonik-2025.12b2.dist-info/WHEEL
aiopythonik-2025.12b2.dist-info/top_level.txt
aiopythonik-2025.12b2.dist-info/RECORD
